{
  "logo": "asset/image/Logo.png",
  "menus": [
    {
      "title": "Flight",
      "url": "#"
    },
    {
      "title": "Hotels",
      "url": "#"
    },
   {
  "title": "Holidays",
  "children": [
    {
      "title": "Domestic",
      "categoryId": "domestic-tours",
      "url": "packages.html?category=domestic-tours"
    
    },
    {
      "title": "International",
      "categoryId": "international",
      "url": "packages.html?category=international"
    }
  ]
},
    {
      "title": "Visa",
      "url": "country_visa.html"
    },
    {
      "title": "Exclusives",
      "children": [
        { "title": "Corporate Tour and Events", "url": "corporate_tour.html" },
        { "title": "Student Tour", "url": "student_tour.html" },
        { "title": "Trade Fair and Exhibitions", "url": "trade_fair.html" },
        { "title": "MICE", "url": "mice.html" },
         { "title": "Destination Weddings", "url": "wedding.html" }
      ]
    },

    {
      "title": "More",
      "children": [
        { "title": "Passport Assistance", "url": "#" },
        { "title": "Travel Insurance", "url": "#" },
        { "title": "Private Transfers", "url": "#" }
      ]
    },
    {
      "title": "Contact Us",
      "url": "contactus.html"
    }
  ]
}
